{
    "pieceCount": 9,
    "targetPositions": [
        {"x": -3.0, "y": 2.0, "z": 0.0},
        {"x": -1.0, "y": 2.0, "z": 0.0},
        {"x": 1.0, "y": 2.0, "z": 0.0},
        {"x": -3.0, "y": 0.0, "z": 0.0},
        {"x": -1.0, "y": 0.0, "z": 0.0},
        {"x": 1.0, "y": 0.0, "z": 0.0},
        {"x": -3.0, "y": -2.0, "z": 0.0},
        {"x": -1.0, "y": -2.0, "z": 0.0},
        {"x": 1.0, "y": -2.0, "z": 0.0}
],
    "pieceSpawnPoints": [
        {"x": 7.0, "y": 3.0, "z": 0.0},
        {"x": -6.0, "y": 0.0, "z": 0.0},
        {"x": 7.0, "y": 0.0, "z": 0.0},
        {"x": 4.0, "y": -3.0, "z": 0.0},
        {"x": 4.0, "y": 3.0, "z": 0.0},
        {"x": -6.0, "y": -3.0, "z": 0.0},
        {"x": -6.0, "y": 3.0, "z": 0.0},
        {"x": 7.0, "y": -3.0, "z": 0.0},
        {"x": 4.0, "y": 0.0, "z": 0.0}
    ],
    "pieceSprites": [
	"EasyLevels/Easy3/Suitcase_0", "EasyLevels/Easy3/Suitcase_1", "EasyLevels/Easy3/Suitcase_2",
	"EasyLevels/Easy3/Suitcase_3", "EasyLevels/Easy3/Suitcase_4", "EasyLevels/Easy3/Suitcase_5",
	"EasyLevels/Easy3/Suitcase_6", "EasyLevels/Easy3/Suitcase_7", "EasyLevels/Easy3/Suitcase_8"
],
	"pieceColliderSize": {"x": 13.33, "y": 13.33},
	"targetSquareColliderSize": {"x": 1, "y": 1},
    "targetScale": {"x": 1.5, "y": 1.5, "z": 1.5},
    "pieceScale": {"x": 0.145, "y": 0.145, "z": 0.145},
    "pieceCorrectOrder": [0, 1, 2, 3, 4, 5, 6, 7, 8]
}